h5writer/__init__.py
h5writer/h5writer.py
h5writer/h5writer_mpi_sw.py
h5writer/h5writer_single.py
h5writer/log.py
h5writer-0.6.0.dist-info/LICENSE
h5writer-0.6.0.dist-info/METADATA
h5writer-0.6.0.dist-info/WHEEL
h5writer-0.6.0.dist-info/top_level.txt
h5writer-0.6.0.dist-info/RECORD
