Metadata-Version: 2.1
Name: h5writer
Version: 0.6.0
Summary: Tool for writing HDF5 files
Home-page: https://github.com/mhantke/h5writer
Author: Max F. Hantke, Benedikt Daurer, Filipe R. N. C. Maia
Author-email: maxhantke@gmail.com
License: MIT License
Platform: UNKNOWN
Classifier: Development Status :: 3 - Alpha
Classifier: Intended Audience :: Developers
Classifier: Topic :: Software Development :: Build Tools
Classifier: License :: OSI Approved :: MIT License
Classifier: Programming Language :: Python :: 2
Classifier: Programming Language :: Python :: 2.7
Classifier: Programming Language :: Python :: 3
Classifier: Programming Language :: Python :: 3.6
Requires-Dist: h5py (>=2.2)
Provides-Extra: mpi
Requires-Dist: mpi4py (>=1.3.1) ; extra == 'mpi'
